[{"Boundaries": [[3751, 3770]], "Type": "Person", "Entity": "johann grubenmann"},{"Boundaries": [[4355, 4369]], "Type": "Person", "Entity": "gustav eiffel"},{"Boundaries": [[2576, 2590]], "Type": "Person", "Entity": "chandragupta i"},{"Boundaries": [[3836, 3850]], "Type": "Person", "Entity": "hubert gautier"},{"Boundaries": [[2454, 2467]], "Type": "Person", "Entity": "jame princep"},{"Boundaries": [[11435, 11438]], "Type": "Organisation", "Entity": "mtr"},{"Boundaries": [[11697, 11720]], "Type": "Organisation", "Entity": "univers of minnesota"},{"Boundaries": [[6507, 6516]], "Type": "PopulatedPlace", "Entity": "louisiana"},{"Boundaries": [[13650, 13660]], "Type": "PopulatedPlace", "Entity": "bratislava"},{"Boundaries": [[12071, 12090]], "Type": "PopulatedPlace", "Entity": "newcastl upon tyne"},{"Boundaries": [[11318, 11327]], "Type": "PopulatedPlace", "Entity": "hong kong"},{"Boundaries": [[12332, 12348]], "Type": "PopulatedPlace", "Entity": "northern ireland"},{"Boundaries": [[2023, 2028]], "Type": "PopulatedPlace", "Entity": "spain"},{"Boundaries": [[3046, 3051], [16561, 16566]], "Type": "PopulatedPlace", "Entity": "china"},{"Boundaries": [[12325, 12330]], "Type": "PopulatedPlace", "Entity": "derri"},{"Boundaries": [[8898, 8907]], "Type": "PopulatedPlace", "Entity": "chongq"},{"Boundaries": [[1514, 1520], [1742, 1748]], "Type": "PopulatedPlace", "Entity": "greec"},{"Boundaries": [[12377, 12387]], "Type": "PopulatedPlace", "Entity": "copenhagen"},{"Boundaries": [[10994, 11004]], "Type": "PopulatedPlace", "Entity": "new jersey"},{"Boundaries": [[10962, 10975]], "Type": "PopulatedPlace", "Entity": "new york citi"},{"Boundaries": [[11736, 11743]], "Type": "PopulatedPlace", "Entity": "toronto"},{"Boundaries": [[8002, 8008], [8039, 8045], [8566, 8572]], "Type": "PopulatedPlace", "Entity": "solkan"},{"Boundaries": [[2879, 2885]], "Type": "PopulatedPlace", "Entity": "mughal"},{"Boundaries": [[8350, 8356]], "Type": "PopulatedPlace", "Entity": "plauen"},{"Boundaries": [[10237, 10248]], "Type": "PopulatedPlace", "Entity": "vladivostok"},{"Boundaries": [[10250, 10256]], "Type": "PopulatedPlace", "Entity": "russia"},{"Boundaries": [[9862, 9867], [14562, 14567]], "Type": "PopulatedPlace", "Entity": "japan"},{"Boundaries": [[16552, 16559]], "Type": "PopulatedPlace", "Entity": "beij"},{}]