[{"Boundaries": [[1677, 1695]], "Type": "Organisation", "Entity": "senat of colombia"},{"Boundaries": [[337, 345], [1643, 1651], [2124, 2132]], "Type": "Organisation", "Entity": "congress"},{"Boundaries": [[1713, 1751]], "Type": "Organisation", "Entity": "chamber of repres of colombia"},{"Boundaries": [[351, 357], [1753, 1761]], "Type": "Organisation", "Entity": "senat"},{"Boundaries": [[16, 24], [130, 138], [394, 402]], "Type": "PopulatedPlace", "Entity": "colombia"},{"Boundaries": [[3226, 3234]], "Type": "PopulatedPlace", "Entity": "mercosur"},{}]