[{"Boundaries": [[770, 776]], "Type": "PopulatedPlace", "Entity": "canada"},{"Boundaries": [[4677, 4685]], "Type": "PopulatedPlace", "Entity": "european"},{"Boundaries": [[6122, 6133]], "Type": "PopulatedPlace", "Entity": "georg town"},{"Boundaries": [[331, 338], [698, 705], [4530, 4537]], "Type": "PopulatedPlace", "Entity": "jamaica"},{"Boundaries": [[72, 86], [225, 239], [494, 508], [629, 643], [1189, 1203], [1590, 1604], [4266, 4280], [4434, 4448], [4570, 4584], [4893, 4907], [5767, 5781], [6194, 6208]], "Type": "PopulatedPlace", "Entity": "cayman island"},{"Boundaries": [[388, 401], [747, 760]], "Type": "PopulatedPlace", "Entity": "unit state"},{"Boundaries": [[4665, 4672]], "Type": "PopulatedPlace", "Entity": "african"},{"Boundaries": [[5630, 5641]], "Type": "PopulatedPlace", "Entity": "philippin"},{"Boundaries": [[5290, 5297]], "Type": "PopulatedPlace", "Entity": "america"},{"Boundaries": [[1473, 1485], [5318, 5330]], "Type": "PopulatedPlace", "Entity": "grand cayman"},{"Boundaries": [[790, 798], [5392, 5400]], "Type": "PopulatedPlace", "Entity": "hondura"},{"Boundaries": [[719, 733]], "Type": "PopulatedPlace", "Entity": "unit kingdom"},{}]