[{"Boundaries": [[28618, 28628]], "Type": "Person", "Entity": "bill jame"},{"Boundaries": [[18391, 18404]], "Type": "Person", "Entity": "dave winfield"},{"Boundaries": [[1079, 1094]], "Type": "Person", "Entity": "abner doubleday"},{"Boundaries": [[16169, 16188], [18605, 18624]], "Type": "Person", "Entity": "georg steinbrenn"},{"Boundaries": [[23673, 23687]], "Type": "Person", "Entity": "roy campanella"},{"Boundaries": [[26065, 26078]], "Type": "Person", "Entity": "georg sisler"},{"Boundaries": [[25961, 25974]], "Type": "Person", "Entity": "ichiro suzuki"},{"Boundaries": [[4100, 4113], [20396, 20409]], "Type": "Person", "Entity": "toni la russa"},{"Boundaries": [[14314, 14325]], "Type": "Person", "Entity": "pat gillick"},{"Boundaries": [[3314, 3331]], "Type": "Person", "Entity": "christi mathewson"},{"Boundaries": [[15825, 15839]], "Type": "Person", "Entity": "catfish hunter"},{"Boundaries": [[23821, 23834]], "Type": "Person", "Entity": "satchel paig"},{"Boundaries": [[18258, 18268]], "Type": "Person", "Entity": "bob howsam"},{"Boundaries": [[4044, 4055], [20913, 20924]], "Type": "Person", "Entity": "greg maddux"},{"Boundaries": [[3962, 3973]], "Type": "Person", "Entity": "effa manley"},{"Boundaries": [[19297, 19308]], "Type": "Person", "Entity": "gari carter"},{"Boundaries": [[3289, 3298], [24365, 24374]], "Type": "Person", "Entity": "babe ruth"},{"Boundaries": [[15406, 15420]], "Type": "Person", "Entity": "frank robinson"},{"Boundaries": [[16255, 16265]], "Type": "Person", "Entity": "nolan ryan"},{"Boundaries": [[669, 690]], "Type": "Person", "Entity": "stephen carlton clark"},{"Boundaries": [[17991, 18006]], "Type": "Person", "Entity": "sparki anderson"},{"Boundaries": [[6584, 6594]], "Type": "Person", "Entity": "addi joss"},{"Boundaries": [[4274, 4285]], "Type": "Person", "Entity": "john smoltz"},{"Boundaries": [[17589, 17601]], "Type": "Person", "Entity": "carlton fisk"},{"Boundaries": [[8053, 8063]], "Type": "Person", "Entity": "lou gehrig"},{"Boundaries": [[3280, 3287]], "Type": "Person", "Entity": "ty cobb"},{"Boundaries": [[4225, 4237]], "Type": "Person", "Entity": "craig biggio"},{"Boundaries": [[3336, 3350]], "Type": "Person", "Entity": "walter johnson"},{"Boundaries": [[18887, 18897], [19742, 19752]], "Type": "Person", "Entity": "wade bogg"},{"Boundaries": [[7506, 7518], [7861, 7873]], "Type": "Person", "Entity": "joe dimaggio"},{"Boundaries": [[27611, 27631]], "Type": "Person", "Entity": "shoeless joe jackson"},{"Boundaries": [[27081, 27091]], "Type": "Person", "Entity": "bowi kuhn"},{"Boundaries": [[20051, 20063]], "Type": "Person", "Entity": "andr dawson"},{"Boundaries": [[4239, 4252]], "Type": "Person", "Entity": "randi johnson"},{"Boundaries": [[1832, 1844]], "Type": "Person", "Entity": "jeff idelson"},{"Boundaries": [[16150, 16164]], "Type": "Person", "Entity": "charl finley"},{"Boundaries": [[13039, 13049]], "Type": "Person", "Entity": "joe gordon"},{"Boundaries": [[27435, 27444]], "Type": "Person", "Entity": "pete rose"},{"Boundaries": [[23655, 23668]], "Type": "Person", "Entity": "johnni podr"},{"Boundaries": [[1338, 1352]], "Type": "Person", "Entity": "dale petroskey"},{"Boundaries": [[17083, 17097]], "Type": "Person", "Entity": "reggi jackson"},{"Boundaries": [[3300, 3312]], "Type": "Person", "Entity": "honu wagner"},{"Boundaries": [[12111, 12123]], "Type": "Person", "Entity": "mike schmidt"},{"Boundaries": [[14466, 14475]], "Type": "Person", "Entity": "ron santo"},{"Boundaries": [[20207, 20219], [21040, 21052]], "Type": "Organisation", "Entity": "chicago cub"},{"Boundaries": [[16508, 16522]], "Type": "Organisation", "Entity": "houston astro"},{"Boundaries": [[23763, 23810]], "Type": "Organisation", "Entity": "all - american girl profession basebal leagu"},{"Boundaries": [[1794, 1815], [3535, 3556]], "Type": "Organisation", "Entity": "major leagu basebal"},{"Boundaries": [[2237, 2255]], "Type": "Organisation", "Entity": "unit state mint"},{"Boundaries": [[16030, 16046], [19808, 19824]], "Type": "Organisation", "Entity": "new york yanke"},{"Boundaries": [[15449, 15466]], "Type": "Organisation", "Entity": "baltimor oriol"},{"Boundaries": [[16739, 16752], [19437, 19450]], "Type": "Organisation", "Entity": "new york met"},{"Boundaries": [[18553, 18569]], "Type": "Organisation", "Entity": "san diego padr"},{"Boundaries": [[15540, 15555], [18055, 18070], [28144, 28159]], "Type": "Organisation", "Entity": "cincinnati red"},{"Boundaries": [[18972, 18992]], "Type": "Organisation", "Entity": "tampa bay devil ray"},{"Boundaries": [[16333, 16346]], "Type": "Organisation", "Entity": "texa ranger"},{"Boundaries": [[18144, 18158]], "Type": "Organisation", "Entity": "detroit tiger"},{"Boundaries": [[25124, 25146]], "Type": "Organisation", "Entity": "world basebal classic"},{"Boundaries": [[17634, 17648], [19945, 19959]], "Type": "Organisation", "Entity": "boston red sox"},{"Boundaries": [[2476, 2514]], "Type": "Organisation", "Entity": "unit state hous of repres"},{"Boundaries": [[17700, 17717], [20477, 20494]], "Type": "Organisation", "Entity": "chicago white sox"},{"Boundaries": [[15992, 16021]], "Type": "Organisation", "Entity": "kansa city/oakland athlet"},{"Boundaries": [[123, 144], [3115, 3136]], "Type": "PopulatedPlace", "Entity": "cooperstown , new york"},{}]