[{"Boundaries": [[3465, 3486]], "Type": "Person", "Entity": "william of malmesburi"},{"Boundaries": [[8039, 8053]], "Type": "Person", "Entity": "hyde wollaston"},{"Boundaries": [[3634, 3645]], "Type": "Person", "Entity": "charlemagn"},{"Boundaries": [[7105, 7114]], "Type": "Person", "Entity": "henri vii"},{"Boundaries": [[2244, 2251], [2918, 2925]], "Type": "Person", "Entity": "henri i"},{"Boundaries": [[8024, 8037]], "Type": "Person", "Entity": "john playfair"},{"Boundaries": [[10217, 10243]], "Type": "Organisation", "Entity": "royal astronom societi"},{"Boundaries": [[7714, 7730], [8611, 8627]], "Type": "Organisation", "Entity": "hous of common"},{"Boundaries": [[6992, 7005], [7992, 8005], [10753, 10766]], "Type": "Organisation", "Entity": "royal societi"},{"Boundaries": [[12781, 12789], [13097, 13105]], "Type": "PopulatedPlace", "Entity": "canadian"},{"Boundaries": [[339, 350], [12161, 12172]], "Type": "PopulatedPlace", "Entity": "new zealand"},{"Boundaries": [[2612, 2622], [2692, 2702]], "Type": "PopulatedPlace", "Entity": "winchest"},{"Boundaries": [[2707, 2713], [5575, 5581], [10770, 10776], [10953, 10959]], "Type": "PopulatedPlace", "Entity": "london"},{"Boundaries": [[134, 147], [393, 406], [459, 472], [10996, 11009], [11120, 11133], [13412, 13425]], "Type": "PopulatedPlace", "Entity": "unit state"},{"Boundaries": [[352, 364], [12178, 12190]], "Type": "PopulatedPlace", "Entity": "south africa"},{"Boundaries": [[320, 329], [12150, 12159]], "Type": "PopulatedPlace", "Entity": "australia"},{"Boundaries": [[370, 384], [12402, 12416], [13290, 13304]], "Type": "PopulatedPlace", "Entity": "unit kingdom"},{}]