[{"Boundaries": [[21835, 21845], [22295, 22305], [22592, 22602]], "Type": "Person", "Entity": "dalai lama"},{"Boundaries": [[11111, 11123]], "Type": "Person", "Entity": "peter singer"},{"Boundaries": [[31444, 31454]], "Type": "Person", "Entity": "yunu emr"},{"Boundaries": [[29828, 29839]], "Type": "Person", "Entity": "max scheler"},{"Boundaries": [[15226, 15239]], "Type": "Person", "Entity": "daniel batson"},{"Boundaries": [[8195, 8207]], "Type": "Person", "Entity": "e . o . wilson"},{"Boundaries": [[11040, 11055]], "Type": "Person", "Entity": "peter kropotkin"},{"Boundaries": [[29121, 29126]], "Type": "Person", "Entity": "comt"},{"Boundaries": [[33387, 33400], [33590, 33603], [33657, 33670], [33939, 33952], [34150, 34163]], "Type": "Person", "Entity": "bhai kanhaiya"},{"Boundaries": [[32381, 32394]], "Type": "Person", "Entity": "yehuda ashlag"},{"Boundaries": [[31865, 31883]], "Type": "Person", "Entity": "abraham isaac kook"},{"Boundaries": [[32175, 32195]], "Type": "Person", "Entity": "mosh chaim luzzatto"},{"Boundaries": [[422, 435], [1958, 1971]], "Type": "Person", "Entity": "august comt"},{"Boundaries": [[29462, 29477]], "Type": "Person", "Entity": "thoma jay oord"},{"Boundaries": [[33240, 33257], [33678, 33695]], "Type": "Person", "Entity": "guru gobind singh"},{"Boundaries": [[11455, 11484], [12459, 12488]], "Type": "Organisation", "Entity": "nation institut of health"},{}]