[{"Boundaries": [[27109, 27120]], "Type": "Person", "Entity": "frank tyson"},{"Boundaries": [[19236, 19250], [47349, 47362]], "Type": "Person", "Entity": "donald bradman"},{"Boundaries": [[40439, 40450]], "Type": "Person", "Entity": "phil hugh"},{"Boundaries": [[26901, 26913]], "Type": "Person", "Entity": "tom graveney"},{"Boundaries": [[46507, 46523]], "Type": "Person", "Entity": "jack warner"},{"Boundaries": [[3351, 3360]], "Type": "Person", "Entity": "ted peat"},{"Boundaries": [[28134, 28145]], "Type": "Person", "Entity": "ian meckiff"},{"Boundaries": [[15868, 15880]], "Type": "Person", "Entity": "hugh trumbl"},{"Boundaries": [[39817, 39830]], "Type": "Person", "Entity": "mickey arthur"},{"Boundaries": [[32169, 32179]], "Type": "Person", "Entity": "ian botham"},{"Boundaries": [[42363, 42375]], "Type": "Person", "Entity": "stuart broad"},{"Boundaries": [[14421, 14432]], "Type": "Person", "Entity": "w . g . grace"},{"Boundaries": [[27929, 27942], [37006, 37019]], "Type": "Person", "Entity": "richi benaud"},{"Boundaries": [[35446, 35459], [37962, 37975]], "Type": "Person", "Entity": "glenn mcgrath"},{"Boundaries": [[18911, 18925]], "Type": "Person", "Entity": "herbi collin"},{"Boundaries": [[27019, 27032]], "Type": "Person", "Entity": "godfrey evan"},{"Boundaries": [[40003, 40015]], "Type": "Person", "Entity": "david warner"},{"Boundaries": [[3495, 3506]], "Type": "Person", "Entity": "harri boyl"},{"Boundaries": [[19576, 19589], [20724, 20737]], "Type": "Person", "Entity": "bill woodful"},{"Boundaries": [[33661, 33675]], "Type": "Person", "Entity": "terri alderman"},{"Boundaries": [[20742, 20755]], "Type": "Person", "Entity": "bill ponsford"},{"Boundaries": [[16857, 16867], [18407, 18417]], "Type": "Person", "Entity": "jack hobb"},{"Boundaries": [[32786, 32796]], "Type": "Person", "Entity": "bob willi"},{"Boundaries": [[14995, 15009]], "Type": "Person", "Entity": "wilfr rhode"},{"Boundaries": [[15204, 15218], [17305, 17319]], "Type": "Person", "Entity": "victor trumper"},{"Boundaries": [[47331, 47343]], "Type": "Person", "Entity": "gari sweet"},{"Boundaries": [[19382, 19395]], "Type": "Person", "Entity": "walli hammond"},{"Boundaries": [[19099, 19116]], "Type": "Person", "Entity": "charli macartney"},{"Boundaries": [[20995, 21004]], "Type": "Person", "Entity": "bill voce"},{"Boundaries": [[34458, 34469]], "Type": "Person", "Entity": "david gower"},{"Boundaries": [[41398, 41402]], "Type": "Person", "Entity": "cook"},{"Boundaries": [[2745, 2757]], "Type": "Person", "Entity": "a . n . hornbi"},{"Boundaries": [[17371, 17386]], "Type": "Person", "Entity": "vernon ransford"},{"Boundaries": [[46486, 46498]], "Type": "Person", "Entity": "terenc rattigan"},{"Boundaries": [[26915, 26928]], "Type": "Person", "Entity": "colin cowdrey"},{"Boundaries": [[5513, 5526], [21862, 21875]], "Type": "Person", "Entity": "pelham warner"},{"Boundaries": [[15406, 15414]], "Type": "Person", "Entity": "jessop'"},{"Boundaries": [[14347, 14361]], "Type": "Person", "Entity": "tom richardson"},{"Boundaries": [[20711, 20722]], "Type": "Person", "Entity": "stan mccabe"},{"Boundaries": [[14615, 14626]], "Type": "Person", "Entity": "harri trott"},{"Boundaries": [[16998, 17011]], "Type": "Person", "Entity": "sydney barn"},{"Boundaries": [[29244, 29254]], "Type": "Person", "Entity": "bill lawri"},{"Boundaries": [[15844, 15855], [16742, 16753]], "Type": "Person", "Entity": "monti nobl"},{"Boundaries": [[26415, 26430]], "Type": "Person", "Entity": "lindsay hassett"},{"Boundaries": [[30099, 30110]], "Type": "Person", "Entity": "john edrich"},{"Boundaries": [[39778, 39792]], "Type": "Person", "Entity": "darren lehmann"},{"Boundaries": [[26952, 26965]], "Type": "Person", "Entity": "brian statham"},{"Boundaries": [[34319, 34329]], "Type": "Person", "Entity": "david boon"},{"Boundaries": [[35670, 35683], [37993, 38006]], "Type": "Person", "Entity": "justin langer"},{"Boundaries": [[13731, 13742]], "Type": "Person", "Entity": "syd gregori"},{"Boundaries": [[31028, 31040]], "Type": "Person", "Entity": "kerri packer"},{"Boundaries": [[26875, 26888]], "Type": "Person", "Entity": "deni compton"},{"Boundaries": [[33940, 33951]], "Type": "Person", "Entity": "chri broad"},{"Boundaries": [[26991, 27000]], "Type": "Person", "Entity": "toni lock"},{"Boundaries": [[14642, 14653]], "Type": "Person", "Entity": "joe darl"},{"Boundaries": [[31771, 31784]], "Type": "Person", "Entity": "mike brearley"},{"Boundaries": [[34683, 34694]], "Type": "Person", "Entity": "neil foster"},{"Boundaries": [[19290, 19300]], "Type": "Person", "Entity": "jack ryder"},{"Boundaries": [[35464, 35479]], "Type": "Person", "Entity": "jason gillespi"},{"Boundaries": [[19121, 19136]], "Type": "Person", "Entity": "warren bardsley"},{"Boundaries": [[33182, 33194]], "Type": "Person", "Entity": "graham gooch"},{"Boundaries": [[29955, 29970]], "Type": "Person", "Entity": "ray illingworth"},{"Boundaries": [[15857, 15866], [17294, 17303]], "Type": "Person", "Entity": "clem hill"},{"Boundaries": [[33533, 33545], [33838, 33850], [35881, 35893]], "Type": "Person", "Entity": "mike gat"},{"Boundaries": [[17595, 17607]], "Type": "Person", "Entity": "ted mcdonald"},{"Boundaries": [[30078, 30094]], "Type": "Person", "Entity": "geoffrey boycott"},{"Boundaries": [[34039, 34054]], "Type": "Person", "Entity": "gladston small"},{"Boundaries": [[29228, 29239]], "Type": "Person", "Entity": "bob simpson"},{"Boundaries": [[34306, 34317]], "Type": "Person", "Entity": "merv hugh"},{"Boundaries": [[34293, 34304]], "Type": "Person", "Entity": "mark taylor"},{"Boundaries": [[26855, 26865], [46669, 46683]], "Type": "Person", "Entity": "len hutton"},{"Boundaries": [[26938, 26950]], "Type": "Person", "Entity": "fred trueman"},{"Boundaries": [[2897, 2908]], "Type": "Person", "Entity": "hugh massi"},{"Boundaries": [[14097, 14110]], "Type": "Person", "Entity": "johnni brigg"},{"Boundaries": [[16959, 16971]], "Type": "Person", "Entity": "frank foster"},{"Boundaries": [[24242, 24256]], "Type": "Person", "Entity": "jack fingleton"},{"Boundaries": [[26980, 26989]], "Type": "Person", "Entity": "jim laker"},{"Boundaries": [[34345, 34356], [35198, 35209], [35283, 35294]], "Type": "Person", "Entity": "steve waugh"},{"Boundaries": [[3845, 3858]], "Type": "Person", "Entity": "charl studd"},{"Boundaries": [[32045, 32057], [33575, 33587], [34240, 34252]], "Type": "Person", "Entity": "allan border"},{"Boundaries": [[33032, 33045]], "Type": "Person", "Entity": "greg chappel"},{"Boundaries": [[24855, 24864]], "Type": "Person", "Entity": "jack ikin"},{"Boundaries": [[20391, 20407]], "Type": "Person", "Entity": "perci hornibrook"},{"Boundaries": [[35611, 35625]], "Type": "Person", "Entity": "adam gilchrist"},{"Boundaries": [[30729, 30742]], "Type": "Person", "Entity": "denni lille"},{"Boundaries": [[38243, 38256]], "Type": "Person", "Entity": "monti panesar"},{"Boundaries": [[28001, 28014]], "Type": "Person", "Entity": "alan davidson"},{"Boundaries": [[16601, 16616]], "Type": "Person", "Entity": "stanley jackson"},{"Boundaries": [[38600, 38615]], "Type": "Person", "Entity": "andrew flintoff"},{"Boundaries": [[30712, 30724]], "Type": "Person", "Entity": "jeff thomson"},{"Boundaries": [[17354, 17366]], "Type": "Person", "Entity": "sammi carter"},{"Boundaries": [[35703, 35717]], "Type": "Person", "Entity": "matthew hayden"},{"Boundaries": [[17340, 17352]], "Type": "Person", "Entity": "tibbi cotter"},{"Boundaries": [[20842, 20857], [47396, 47406]], "Type": "Person", "Entity": "dougla jardin"},{"Boundaries": [[20695, 20709]], "Type": "Person", "Entity": "archi jackson"},{"Boundaries": [[19468, 19481]], "Type": "Person", "Entity": "patsi hendren"},{"Boundaries": [[14462, 14468], [35394, 35398]], "Type": "Person", "Entity": "mark"},{"Boundaries": [[47369, 47378]], "Type": "Person", "Entity": "hugo weav"},{"Boundaries": [[35810, 35821], [37977, 37988]], "Type": "Person", "Entity": "shane warn"},{"Boundaries": [[35685, 35698], [38058, 38071]], "Type": "Person", "Entity": "damien martyn"},{"Boundaries": [[38224, 38238], [40268, 40282]], "Type": "Person", "Entity": "jame anderson"},{"Boundaries": [[34331, 34340], [35572, 35581]], "Type": "Person", "Entity": "ian heali"},{"Boundaries": [[26285, 26297]], "Type": "Person", "Entity": "eric holli"},{"Boundaries": [[34021, 34034]], "Type": "Person", "Entity": "graham dilley"},{"Boundaries": [[24656, 24668]], "Type": "Person", "Entity": "keith miller"},{"Boundaries": [[26967, 26978]], "Type": "Person", "Entity": "alec bedser"},{"Boundaries": [[15812, 15829], [17321, 17338]], "Type": "Person", "Entity": "warwick armstrong"},{"Boundaries": [[24639, 24651]], "Type": "Person", "Entity": "ray lindwal"},{"Boundaries": [[39947, 39960]], "Type": "Person", "Entity": "ricki pont"},{"Boundaries": [[42046, 42050]], "Type": "Person", "Entity": "bell"},{"Boundaries": [[30919, 30929]], "Type": "Person", "Entity": "toni greig"},{"Boundaries": [[20976, 20990]], "Type": "Person", "Entity": "harold larwood"},{"Boundaries": [[3069, 3083]], "Type": "Person", "Entity": "fred spofforth"},{"Boundaries": [[5331, 5344], [13748, 13761]], "Type": "Person", "Entity": "georg giffen"},{"Boundaries": [[18422, 18439]], "Type": "Person", "Entity": "herbert sutcliff"},{"Boundaries": [[33199, 33211], [34699, 34711]], "Type": "Person", "Entity": "john emburey"},{"Boundaries": [[13889, 13899]], "Type": "Person", "Entity": "bobbi peel"},{"Boundaries": [[9841, 9864]], "Type": "Organisation", "Entity": "marylebon cricket club"},{"Boundaries": [[46082, 46103]], "Type": "Organisation", "Entity": "rugbi leagu \"ashes\""},{"Boundaries": [[48220, 48247]], "Type": "Organisation", "Entity": "ultim fight championship"},{"Boundaries": [[46047, 46059]], "Type": "Organisation", "Entity": "great britain"},{"Boundaries": [[45313, 45316]], "Type": "PopulatedPlace", "Entity": "kennington"},{"Boundaries": [[45687, 45689]], "Type": "PopulatedPlace", "Entity": "sheffield"},{"Boundaries": [[7380, 7397]], "Type": "PopulatedPlace", "Entity": "sunburi , victoria"},{"Boundaries": [[6955, 6964]], "Type": "PopulatedPlace", "Entity": "victorian"},{"Boundaries": [[9404, 9410]], "Type": "PopulatedPlace", "Entity": "dublin"},{"Boundaries": [[45604, 45607]], "Type": "PopulatedPlace", "Entity": "chester - le - street"},{"Boundaries": [[45410, 45415]], "Type": "PopulatedPlace", "Entity": "north london"},{"Boundaries": [[45482, 45497]], "Type": "PopulatedPlace", "Entity": "leed"},{"Boundaries": [[14928, 14937], [38384, 38393], [45506, 45516]], "Type": "PopulatedPlace", "Entity": "edgbaston"},{"Boundaries": [[45442, 45455]], "Type": "PopulatedPlace", "Entity": "west bridgford"},{"Boundaries": [[45317, 45325]], "Type": "PopulatedPlace", "Entity": "south london"},{"Boundaries": [[881, 890], [9196, 9205], [38906, 38915], [44787, 44789], [44950, 44956]], "Type": "PopulatedPlace", "Entity": "melbourn"},{"Boundaries": [[38180, 38187], [45558, 45563]], "Type": "PopulatedPlace", "Entity": "cardiff"},{}]