[{"Boundaries": [[14304, 14324]], "Type": "Person", "Entity": "alexand bulatovich"},{"Boundaries": [[9675, 9688]], "Type": "Person", "Entity": "hosni mubarak"},{"Boundaries": [[7192, 7205]], "Type": "Person", "Entity": "seyoum mesfin"},{"Boundaries": [[1796, 1801]], "Type": "Organisation", "Entity": "korea"},{"Boundaries": [[3831, 3861], [10529, 10559]], "Type": "Organisation", "Entity": "feder parliamentari assembl"},{"Boundaries": [[10053, 10071]], "Type": "Organisation", "Entity": "ethiopian airlin"},{"Boundaries": [[10035, 10048]], "Type": "Organisation", "Entity": "sudan airway"},{"Boundaries": [[16768, 16774]], "Type": "PopulatedPlace", "Entity": "canada"},{"Boundaries": [[13935, 13945]], "Type": "PopulatedPlace", "Entity": "tajikistan"},{"Boundaries": [[16221, 16233]], "Type": "PopulatedPlace", "Entity": "kuala lumpur"},{"Boundaries": [[12197, 12204], [12249, 12256]], "Type": "PopulatedPlace", "Entity": "finland"},{"Boundaries": [[8764, 8799]], "Type": "PopulatedPlace", "Entity": "transit feder govern"},{"Boundaries": [[16434, 16448], [16506, 16511], [16610, 16615]], "Type": "PopulatedPlace", "Entity": "qatar"},{"Boundaries": [[12067, 12074], [12078, 12085]], "Type": "PopulatedPlace", "Entity": "denmark"},{"Boundaries": [[10936, 10950], [11393, 11408]], "Type": "PopulatedPlace", "Entity": "gambela region"},{"Boundaries": [[13487, 13494]], "Type": "PopulatedPlace", "Entity": "austria"},{"Boundaries": [[11494, 11504]], "Type": "PopulatedPlace", "Entity": "al qadarif"},{"Boundaries": [[1255, 1262], [2572, 2579], [5023, 5030], [5701, 5708], [5710, 5717]], "Type": "PopulatedPlace", "Entity": "eritrea"},{"Boundaries": [[941, 958], [17024, 17041]], "Type": "PopulatedPlace", "Entity": "leagu of nation"},{"Boundaries": [[3016, 3029]], "Type": "PopulatedPlace", "Entity": "african union"},{"Boundaries": [[14614, 14621]], "Type": "PopulatedPlace", "Entity": "ottoman"},{"Boundaries": [[10377, 10387]], "Type": "PopulatedPlace", "Entity": "port sudan"},{"Boundaries": [[2903, 2914], [4188, 4208], [6303, 6314], [6695, 6706], [9733, 9744], [10321, 10332], [12104, 12115], [12275, 12286], [12387, 12398], [13003, 13014], [13370, 13381], [13525, 13536], [13756, 13767], [14525, 14536], [14988, 14999], [15207, 15218], [15399, 15410], [15593, 15604], [16417, 16428], [16673, 16684], [16793, 16804], [17113, 17124], [17285, 17296], [17811, 17822]], "Type": "PopulatedPlace", "Entity": "addi ababa"},{"Boundaries": [[13412, 13416]], "Type": "PopulatedPlace", "Entity": "rome"},{"Boundaries": [[2536, 2545]], "Type": "PopulatedPlace", "Entity": "mogadishu"},{"Boundaries": [[2873, 2878], [15198, 15203], [15221, 15226], [15361, 15373], [15423, 15428]], "Type": "PopulatedPlace", "Entity": "india"},{"Boundaries": [[14231, 14235]], "Type": "PopulatedPlace", "Entity": "derg"},{"Boundaries": [[6000, 6005], [6153, 6158], [6250, 6255], [6276, 6281], [6398, 6403]], "Type": "PopulatedPlace", "Entity": "kenya"},{"Boundaries": [[2847, 2852], [14883, 14888], [14964, 14969]], "Type": "PopulatedPlace", "Entity": "china"},{"Boundaries": [[13961, 13968]], "Type": "PopulatedPlace", "Entity": "ukrain"},{"Boundaries": [[7799, 7813]], "Type": "PopulatedPlace", "Entity": "adal sultan"},{"Boundaries": [[17372, 17385], [17469, 17482], [17779, 17792]], "Type": "PopulatedPlace", "Entity": "unit state"},{"Boundaries": [[16643, 16654]], "Type": "PopulatedPlace", "Entity": "south korea"},{"Boundaries": [[13479, 13485]], "Type": "PopulatedPlace", "Entity": "vienna"},{"Boundaries": [[8000, 8006], [8128, 8134]], "Type": "PopulatedPlace", "Entity": "ogaden"},{"Boundaries": [[11363, 11380]], "Type": "PopulatedPlace", "Entity": "benishangul - gumuz"},{"Boundaries": [[2862, 2868], [16948, 16954], [17182, 17188], [17224, 17230], [17260, 17266], [17326, 17332]], "Type": "PopulatedPlace", "Entity": "mexico"},{"Boundaries": [[2304, 2312], [3154, 3162], [3609, 3617], [3754, 3762], [4194, 4208], [11868, 11876]], "Type": "PopulatedPlace", "Entity": "djibouti"},{"Boundaries": [[11483, 11489]], "Type": "PopulatedPlace", "Entity": "sennar"},{"Boundaries": [[13902, 13912]], "Type": "PopulatedPlace", "Entity": "kazakhstan"},{"Boundaries": [[5686, 5691]], "Type": "PopulatedPlace", "Entity": "badm"},{"Boundaries": [[13947, 13959]], "Type": "PopulatedPlace", "Entity": "turkmenistan"},{"Boundaries": [[557, 565], [1518, 1526], [1646, 1654], [1710, 1718], [2077, 2085], [2264, 2272], [2806, 2814], [3141, 3149], [3654, 3662], [3987, 3995], [4888, 4896], [5056, 5064], [5145, 5153], [6010, 6018], [6207, 6215], [6385, 6393], [6641, 6649], [6757, 6765], [6818, 6826], [7411, 7419], [7922, 7930], [9203, 9211], [9278, 9286], [9359, 9367], [10172, 10180], [11596, 11604], [11671, 11679], [11878, 11886], [12028, 12036], [12117, 12125], [12170, 12178], [12791, 12799], [12928, 12936], [13131, 13139], [13385, 13393], [13421, 13429], [13771, 13779], [14283, 14291], [14463, 14471], [14682, 14690], [14900, 14908], [15039, 15047], [15157, 15165], [15475, 15483], [15529, 15537], [15702, 15710], [15844, 15858], [15881, 15889], [16185, 16193], [16278, 16286], [16374, 16382], [16434, 16448], [16461, 16469], [16808, 16816], [17126, 17134], [17300, 17308], [17430, 17438], [17548, 17556], [17695, 17703]], "Type": "PopulatedPlace", "Entity": "ethiopia"},{"Boundaries": [[16389, 16398]], "Type": "PopulatedPlace", "Entity": "palestin"},{"Boundaries": [[6831, 6838]], "Type": "PopulatedPlace", "Entity": "liberia"},{"Boundaries": [[8536, 8556]], "Type": "PopulatedPlace", "Entity": "islam court union"},{"Boundaries": [[12955, 12961]], "Type": "PopulatedPlace", "Entity": "dublin"},{"Boundaries": [[11382, 11388]], "Type": "PopulatedPlace", "Entity": "amhara"},{"Boundaries": [[17764, 17775]], "Type": "PopulatedPlace", "Entity": "lo angel"},{"Boundaries": [[12977, 12984]], "Type": "PopulatedPlace", "Entity": "ireland"},{"Boundaries": [[13893, 13900]], "Type": "PopulatedPlace", "Entity": "georgia"},{"Boundaries": [[13926, 13933]], "Type": "PopulatedPlace", "Entity": "moldova"},{"Boundaries": [[13974, 13984]], "Type": "PopulatedPlace", "Entity": "uzbekistan"},{"Boundaries": [[4901, 4906], [12478, 12483], [13051, 13056], [13346, 13351]], "Type": "PopulatedPlace", "Entity": "itali"},{"Boundaries": [[1287, 1292], [2317, 2322], [4569, 4574], [9291, 9296], [9372, 9377], [9789, 9794], [9888, 9893], [10162, 10167], [10623, 10628], [11554, 11559], [11742, 11747], [11846, 11851], [11891, 11896], [14421, 14426]], "Type": "PopulatedPlace", "Entity": "sudan"},{"Boundaries": [[7847, 7854], [8154, 8160], [8369, 8375], [8447, 8453], [9073, 9079]], "Type": "PopulatedPlace", "Entity": "somali"},{"Boundaries": [[2854, 2860], [15568, 15574], [15635, 15641], [15829, 15835]], "Type": "PopulatedPlace", "Entity": "israel"},{"Boundaries": [[16241, 16249], [16290, 16298]], "Type": "PopulatedPlace", "Entity": "malaysia"},{"Boundaries": [[14500, 14506], [14631, 14637]], "Type": "PopulatedPlace", "Entity": "turkey"},{"Boundaries": [[2132, 2144], [14160, 14172]], "Type": "PopulatedPlace", "Entity": "soviet union"},{"Boundaries": [[310, 319]], "Type": "PopulatedPlace", "Entity": "jerusalem"},{"Boundaries": [[9959, 9966]], "Type": "PopulatedPlace", "Entity": "gambela"},{"Boundaries": [[12460, 12467], [12664, 12671], [12688, 12695]], "Type": "PopulatedPlace", "Entity": "germani"},{"Boundaries": [[11355, 11361]], "Type": "PopulatedPlace", "Entity": "tigray"},{"Boundaries": [[13872, 13882]], "Type": "PopulatedPlace", "Entity": "azerbaijan"},{"Boundaries": [[2438, 2445], [7399, 7406], [7910, 7917], [8710, 8717], [8856, 8863]], "Type": "PopulatedPlace", "Entity": "somalia"},{"Boundaries": [[13863, 13870]], "Type": "PopulatedPlace", "Entity": "armenia"},{"Boundaries": [[11055, 11068]], "Type": "PopulatedPlace", "Entity": "amhara region"},{"Boundaries": [[13721, 13727], [13834, 13840], [14058, 14064]], "Type": "PopulatedPlace", "Entity": "russia"},{"Boundaries": [[15184, 15193]], "Type": "PopulatedPlace", "Entity": "new delhi"},{"Boundaries": [[13448, 13455], [13499, 13506], [13671, 13678]], "Type": "PopulatedPlace", "Entity": "romania"},{"Boundaries": [[15844, 15858], [15871, 15876]], "Type": "PopulatedPlace", "Entity": "japan"},{"Boundaries": [[13884, 13891]], "Type": "PopulatedPlace", "Entity": "belaru"},{"Boundaries": [[7752, 7768]], "Type": "PopulatedPlace", "Entity": "ethiopian empir"},{"Boundaries": [[6654, 6661], [6663, 6670], [6748, 6755], [6953, 6960]], "Type": "PopulatedPlace", "Entity": "namibia"},{"Boundaries": [[14927, 14934]], "Type": "PopulatedPlace", "Entity": "beij"},{"Boundaries": [[12056, 12065]], "Type": "PopulatedPlace", "Entity": "svendborg"},{"Boundaries": [[1747, 1761], [2954, 2968], [6937, 6951]], "Type": "PopulatedPlace", "Entity": "unit nation"},{"Boundaries": [[14490, 14496]], "Type": "PopulatedPlace", "Entity": "ankara"},{"Boundaries": [[2028, 2048]], "Type": "PopulatedPlace", "Entity": "non - align movement"},{}]