[{"Boundaries": [[25178, 25195]], "Type": "Person", "Entity": "david d . friedman"},{"Boundaries": [[28276, 28292]], "Type": "Person", "Entity": "andrew bernstein"},{"Boundaries": [[32497, 32514]], "Type": "Person", "Entity": "nathaniel branden"},{"Boundaries": [[237, 252], [2856, 2871], [23165, 23180], [27902, 27917]], "Type": "Person", "Entity": "leonard peikoff"},{"Boundaries": [[28018, 28041]], "Type": "Person", "Entity": "chri matthew sciabarra"},{"Boundaries": [[25230, 25247]], "Type": "Person", "Entity": "chandran kukatha"},{"Boundaries": [[28184, 28198], [31819, 31833]], "Type": "Person", "Entity": "allan gotthelf"},{"Boundaries": [[23185, 23196]], "Type": "Person", "Entity": "yaron brook"},{"Boundaries": [[18742, 18755]], "Type": "Person", "Entity": "robert nozick"},{"Boundaries": [[29815, 29829]], "Type": "Person", "Entity": "edwin a . lock"},{"Boundaries": [[28219, 28234]], "Type": "Person", "Entity": "tibor r . machan"},{"Boundaries": [[29167, 29177]], "Type": "Person", "Entity": "tara smith"},{"Boundaries": [[29665, 29679]], "Type": "Person", "Entity": "georg reisman"},{"Boundaries": [[25197, 25207]], "Type": "Person", "Entity": "roy child"},{"Boundaries": [[28605, 28617]], "Type": "Person", "Entity": "david kelley"},{"Boundaries": [[31785, 31794]], "Type": "Person", "Entity": "aristotl"},{"Boundaries": [[25161, 25176]], "Type": "Person", "Entity": "murray rothbard"},{"Boundaries": [[28531, 28543]], "Type": "Person", "Entity": "j . l . austin"},{"Boundaries": [[28548, 28562]], "Type": "Person", "Entity": "gilbert harman"},{"Boundaries": [[30165, 30181]], "Type": "Person", "Entity": "harri binswang"},{"Boundaries": [[75, 83], [1644, 1652], [13331, 13339], [27959, 27967], [28115, 28123], [28172, 28180], [28207, 28215], [28866, 28874], [31630, 31638], [32086, 32094], [33290, 33298]], "Type": "Person", "Entity": "ayn rand"},{"Boundaries": [[32122, 32146], [32271, 32295]], "Type": "Organisation", "Entity": "univers of pittsburgh"},{"Boundaries": [[32602, 32620]], "Type": "Organisation", "Entity": "ayn rand institut"},{"Boundaries": [[32297, 32326]], "Type": "Organisation", "Entity": "univers of texa at austin"},{"Boundaries": [[32331, 32374]], "Type": "Organisation", "Entity": "univers of north carolina at chapel hill"},{}]