[{"Boundaries": [[6427, 6441]], "Type": "Person", "Entity": "aleksandra mir"},{"Boundaries": [[8340, 8355]], "Type": "Person", "Entity": "gunnar svedberg"},{"Boundaries": [[6962, 6976]], "Type": "Person", "Entity": "ernst cassir"},{"Boundaries": [[6132, 6144]], "Type": "Person", "Entity": "jan eliasson"},{"Boundaries": [[8155, 8168]], "Type": "Person", "Entity": "hjalmar frisk"},{"Boundaries": [[5893, 5907]], "Type": "Person", "Entity": "perci barnevik"},{"Boundaries": [[7898, 7908]], "Type": "Person", "Entity": "linda haa"},{"Boundaries": [[7846, 7855]], "Type": "Person", "Entity": "david cox"},{"Boundaries": [[7529, 7541]], "Type": "Person", "Entity": "bo rothstein"},{"Boundaries": [[7341, 7353]], "Type": "Person", "Entity": "lotta lotass"},{"Boundaries": [[6905, 6919]], "Type": "Person", "Entity": "arvid carlsson"},{"Boundaries": [[5960, 5972]], "Type": "Person", "Entity": "nick bostrom"},{"Boundaries": [[7249, 7266], [8100, 8117]], "Type": "Person", "Entity": "bernhard karlgren"},{"Boundaries": [[6106, 6121]], "Type": "Person", "Entity": "magnu carlsson"},{"Boundaries": [[8130, 8142]], "Type": "Person", "Entity": "curt weibul"},{"Boundaries": [[7476, 7484]], "Type": "Person", "Entity": "bo ralph"},{"Boundaries": [[6552, 6566]], "Type": "Person", "Entity": "susanna roxman"},{"Boundaries": [[6597, 6615]], "Type": "Person", "Entity": "maria wetterstrand"},{"Boundaries": [[6291, 6314]], "Type": "Person", "Entity": "carl henrik fredriksson"},{"Boundaries": [[6644, 6663]], "Type": "Person", "Entity": "muhammad al - yaqoubi"},{"Boundaries": [[4, 28], [95, 119], [337, 361], [1154, 1178], [1893, 1917], [2246, 2270], [2627, 2651], [5405, 5429], [7585, 7609]], "Type": "Organisation", "Entity": "univers of gothenburg"},{"Boundaries": [[4162, 4195]], "Type": "Organisation", "Entity": "chalmer univers of technolog"},{"Boundaries": [[1296, 1314]], "Type": "Organisation", "Entity": "uppsala univers"},{"Boundaries": [[7125, 7142]], "Type": "Organisation", "Entity": "academia europaea"},{"Boundaries": [[6052, 6069]], "Type": "Organisation", "Entity": "oxford univers"},{"Boundaries": [[2483, 2490]], "Type": "Organisation", "Entity": "uppsala"},{"Boundaries": [[6862, 6877], [7069, 7084], [7398, 7413], [7457, 7472], [7510, 7525]], "Type": "Organisation", "Entity": "swedish academi"},{"Boundaries": [[7028, 7061]], "Type": "Organisation", "Entity": "royal swedish academi of scienc"},{"Boundaries": [[2502, 2511]], "Type": "Organisation", "Entity": "stockholm"},{"Boundaries": [[6629, 6640]], "Type": "Organisation", "Entity": "green parti"},{"Boundaries": [[2492, 2496]], "Type": "Organisation", "Entity": "lund"},{"Boundaries": [[1319, 1334]], "Type": "Organisation", "Entity": "lund univers"},{"Boundaries": [[429, 435], [796, 802], [2589, 2595], [6281, 6287]], "Type": "PopulatedPlace", "Entity": "sweden"},{"Boundaries": [[78, 88], [627, 637], [814, 824], [1214, 1224], [1704, 1714], [1762, 1772], [1824, 1834], [2221, 2231], [2365, 2375], [2456, 2466], [4274, 4284]], "Type": "PopulatedPlace", "Entity": "gothenburg"},{"Boundaries": [[7743, 7750]], "Type": "PopulatedPlace", "Entity": "iceland"},{"Boundaries": [[261, 277]], "Type": "PopulatedPlace", "Entity": "nordic countri"},{}]