[{"Boundaries": [[17728, 17739]], "Type": "Person", "Entity": "vess ossman"},{"Boundaries": [[34555, 34568]], "Type": "Person", "Entity": "johnni hodg"},{"Boundaries": [[74903, 74913]], "Type": "Person", "Entity": "al jarreau"},{"Boundaries": [[50636, 50642]], "Type": "Person", "Entity": "sun ra"},{"Boundaries": [[52757, 52776]], "Type": "Person", "Entity": "albert mangelsdorff"},{"Boundaries": [[23473, 23485]], "Type": "Person", "Entity": "buddi bolden"},{"Boundaries": [[79107, 79129]], "Type": "Person", "Entity": "ronald shannon jackson"},{"Boundaries": [[75016, 75027]], "Type": "Person", "Entity": "kirk whalum"},{"Boundaries": [[79056, 79070]], "Type": "Person", "Entity": "sonni sharrock"},{"Boundaries": [[18875, 18887]], "Type": "Person", "Entity": "ned sublett"},{"Boundaries": [[46498, 46510]], "Type": "Person", "Entity": "dave brubeck"},{"Boundaries": [[62107, 62122]], "Type": "Person", "Entity": "langston hugh"},{"Boundaries": [[49144, 49157], [61878, 61891]], "Type": "Person", "Entity": "jacki mclean"},{"Boundaries": [[70508, 70522]], "Type": "Person", "Entity": "sonni bradshaw"},{"Boundaries": [[78076, 78087]], "Type": "Person", "Entity": "easi mo bee"},{"Boundaries": [[75029, 75040]], "Type": "Person", "Entity": "boney jame"},{"Boundaries": [[32491, 32504], [33225, 33238]], "Type": "Person", "Entity": "paul whiteman"},{"Boundaries": [[74136, 74153]], "Type": "Person", "Entity": "mari lou william"},{"Boundaries": [[46990, 47005]], "Type": "Person", "Entity": "lenni tristano"},{"Boundaries": [[50554, 50569], [78976, 78991], [82158, 82173]], "Type": "Person", "Entity": "ornett coleman"},{"Boundaries": [[59542, 59555], [68159, 68172]], "Type": "Person", "Entity": "airto moreira"},{"Boundaries": [[4796, 4810], [31126, 31140], [39212, 39226], [73477, 73491]], "Type": "Person", "Entity": "duke ellington"},{"Boundaries": [[3441, 3462]], "Type": "Person", "Entity": "joachim - ernst berendt"},{"Boundaries": [[44844, 44855], [63025, 63036]], "Type": "Person", "Entity": "willi bobo"},{"Boundaries": [[47729, 47743]], "Type": "Person", "Entity": "clifford brown"},{"Boundaries": [[31902, 31916]], "Type": "Person", "Entity": "lionel hampton"},{"Boundaries": [[9544, 9560]], "Type": "Person", "Entity": "jimmi mcpartland"},{"Boundaries": [[48408, 48422]], "Type": "Person", "Entity": "georg russel"},{"Boundaries": [[76117, 76126]], "Type": "Person", "Entity": "roy ayer"},{"Boundaries": [[31088, 31100]], "Type": "Person", "Entity": "cab calloway"},{"Boundaries": [[48188, 48199], [64377, 64388], [65374, 65385]], "Type": "Person", "Entity": "mark levin"},{"Boundaries": [[47701, 47714], [61016, 61029]], "Type": "Person", "Entity": "horac silver"},{"Boundaries": [[81565, 81578]], "Type": "Person", "Entity": "stefon harri"},{"Boundaries": [[34596, 34611]], "Type": "Person", "Entity": "cooti william"},{"Boundaries": [[81711, 81728]], "Type": "Person", "Entity": "christian mcbride"},{"Boundaries": [[33305, 33321]], "Type": "Person", "Entity": "django reinhardt"},{"Boundaries": [[59409, 59422]], "Type": "Person", "Entity": "frank sinatra"},{"Boundaries": [[61413, 61431], [62204, 62222]], "Type": "Person", "Entity": "stanley turrentin"},{"Boundaries": [[69702, 69713], [73659, 73670]], "Type": "Person", "Entity": "chick corea"},{"Boundaries": [[71794, 71806]], "Type": "Person", "Entity": "rufu harley"},{"Boundaries": [[81249, 81260]], "Type": "Person", "Entity": "norah jone"},{"Boundaries": [[74424, 74436]], "Type": "Person", "Entity": "david murray"},{"Boundaries": [[46887, 46901]], "Type": "Person", "Entity": "bengt hallberg"},{"Boundaries": [[9531, 9542]], "Type": "Person", "Entity": "bud freeman"},{"Boundaries": [[80324, 80336]], "Type": "Person", "Entity": "brad mehldau"},{"Boundaries": [[41711, 41722], [46390, 46401], [48424, 48435], [59902, 59913], [63275, 63286], [68552, 68563], [69649, 69660], [70991, 71002], [73719, 73730]], "Type": "Person", "Entity": "mile davi"},{"Boundaries": [[65782, 65793], [69865, 69876]], "Type": "Person", "Entity": "frank zappa"},{"Boundaries": [[81534, 81550]], "Type": "Person", "Entity": "kurt rosenwinkel"},{"Boundaries": [[81262, 81278]], "Type": "Person", "Entity": "cassandra wilson"},{"Boundaries": [[33704, 33714]], "Type": "Person", "Entity": "joe venuti"},{"Boundaries": [[29458, 29473]], "Type": "Person", "Entity": "coleman hawkin"},{"Boundaries": [[66675, 66686]], "Type": "Person", "Entity": "jame brown"},{"Boundaries": [[52131, 52146]], "Type": "Person", "Entity": "pharoah sander"},{"Boundaries": [[81280, 81291]], "Type": "Person", "Entity": "kurt ell"},{"Boundaries": [[52778, 52791], [72223, 72236]], "Type": "Person", "Entity": "kenni wheeler"},{"Boundaries": [[42450, 42460], [42556, 42566]], "Type": "Person", "Entity": "chano pozo"},{"Boundaries": [[55006, 55016], [55596, 55606]], "Type": "Person", "Entity": "cal tjader"},{"Boundaries": [[50839, 50851]], "Type": "Person", "Entity": "sunni murray"},{"Boundaries": [[74943, 74947]], "Type": "Person", "Entity": "sade"},{"Boundaries": [[38976, 38990], [39090, 39104]], "Type": "Person", "Entity": "claud debussi"},{"Boundaries": [[69744, 69755]], "Type": "Person", "Entity": "gari burton"},{"Boundaries": [[41378, 41392]], "Type": "Person", "Entity": "bobbi sanabria"},{"Boundaries": [[76131, 76142]], "Type": "Person", "Entity": "donald byrd"},{"Boundaries": [[81684, 81697]], "Type": "Person", "Entity": "ken peplowski"},{"Boundaries": [[31931, 31948]], "Type": "Person", "Entity": "charli christian"},{"Boundaries": [[55809, 55820]], "Type": "Person", "Entity": "tito puent"},{"Boundaries": [[46535, 46544], [59237, 59246]], "Type": "Person", "Entity": "stan getz"},{"Boundaries": [[62916, 62929]], "Type": "Person", "Entity": "paul chamber"},{"Boundaries": [[78765, 78774]], "Type": "Person", "Entity": "john zorn"},{"Boundaries": [[72238, 72249]], "Type": "Person", "Entity": "john taylor"},{"Boundaries": [[69662, 69674]], "Type": "Person", "Entity": "eddi harri"},{"Boundaries": [[72209, 72221]], "Type": "Person", "Entity": "ralph towner"},{"Boundaries": [[49629, 49639]], "Type": "Person", "Entity": "brew moor"},{"Boundaries": [[12629, 12652], [16133, 16156]], "Type": "Person", "Entity": "loui moreau gottschalk"},{"Boundaries": [[64281, 64294]], "Type": "Person", "Entity": "joe henderson"},{"Boundaries": [[52796, 52810]], "Type": "Person", "Entity": "mike westbrook"},{"Boundaries": [[47672, 47678]], "Type": "Person", "Entity": "blakey"},{"Boundaries": [[74915, 74926]], "Type": "Person", "Entity": "anita baker"},{"Boundaries": [[53104, 53115]], "Type": "Person", "Entity": "han bennink"},{"Boundaries": [[9640, 9653], [31142, 31155], [31847, 31860]], "Type": "Person", "Entity": "benni goodman"},{"Boundaries": [[44824, 44838]], "Type": "Person", "Entity": "armando peraza"},{"Boundaries": [[52510, 52521]], "Type": "Person", "Entity": "eric dolphi"},{"Boundaries": [[31206, 31216]], "Type": "Person", "Entity": "arti shaw"},{"Boundaries": [[9562, 9580]], "Type": "Person", "Entity": "frank teschemach"},{"Boundaries": [[66503, 66513], [71539, 71549]], "Type": "Person", "Entity": "teo macero"},{"Boundaries": [[69936, 69950]], "Type": "Person", "Entity": "stanley clark"},{"Boundaries": [[69817, 69830]], "Type": "Person", "Entity": "larri coryel"},{"Boundaries": [[72161, 72170]], "Type": "Person", "Entity": "paul bley"},{"Boundaries": [[3039, 3052]], "Type": "Person", "Entity": "j . j . johnson"},{"Boundaries": [[17664, 17676]], "Type": "Person", "Entity": "ernest hogan"},{"Boundaries": [[49661, 49674]], "Type": "Person", "Entity": "flip phillip"},{"Boundaries": [[81236, 81247]], "Type": "Person", "Entity": "diana krall"},{"Boundaries": [[14722, 14738], [21454, 21470]], "Type": "Person", "Entity": "gunther schuller"},{"Boundaries": [[69845, 69860]], "Type": "Person", "Entity": "john mclaughlin"},{"Boundaries": [[45721, 45733]], "Type": "Person", "Entity": "ward kimbal"},{"Boundaries": [[69790, 69804], [71763, 71777]], "Type": "Person", "Entity": "jean - luc ponti"},{"Boundaries": [[60420, 60430], [61841, 61851]], "Type": "Person", "Entity": "lee morgan"},{"Boundaries": [[74983, 75004]], "Type": "Person", "Entity": "grover washington , jr ."},{"Boundaries": [[28737, 28749]], "Type": "Person", "Entity": "bessi smith"},{"Boundaries": [[32471, 32489]], "Type": "Person", "Entity": "jame rees europ"},{"Boundaries": [[20110, 20121], [20145, 20156]], "Type": "Person", "Entity": "w . c . handi"},{"Boundaries": [[81512, 81522]], "Type": "Person", "Entity": "vijay iyer"},{"Boundaries": [[46512, 46522], [49229, 49239], [59915, 59925]], "Type": "Person", "Entity": "bill evan"},{"Boundaries": [[32214, 32226]], "Type": "Person", "Entity": "lester young"},{"Boundaries": [[81496, 81507]], "Type": "Person", "Entity": "jason moran"},{"Boundaries": [[9145, 9157]], "Type": "Person", "Entity": "amiri baraka"},{"Boundaries": [[57575, 57591], [60327, 60338], [63902, 63913]], "Type": "Person", "Entity": "mccoy tyner"},{"Boundaries": [[50622, 50634], [50968, 50980]], "Type": "Person", "Entity": "archi shepp"},{"Boundaries": [[80731, 80744]], "Type": "Person", "Entity": "charl gayl"},{"Boundaries": [[79089, 79101]], "Type": "Person", "Entity": "bill laswel"},{"Boundaries": [[65765, 65777], [66712, 66724]], "Type": "Person", "Entity": "jimi hendrix"},{"Boundaries": [[31075, 31086]], "Type": "Person", "Entity": "count basi"},{"Boundaries": [[69832, 69843]], "Type": "Person", "Entity": "al di meola"},{"Boundaries": [[81297, 81309]], "Type": "Person", "Entity": "jami cullum"},{"Boundaries": [[9582, 9592]], "Type": "Person", "Entity": "dave tough"},{"Boundaries": [[69689, 69700]], "Type": "Person", "Entity": "joe zawinul"},{"Boundaries": [[75007, 75014]], "Type": "Person", "Entity": "kenni g"},{"Boundaries": [[74440, 74450]], "Type": "Person", "Entity": "don pullen"},{"Boundaries": [[67037, 67048]], "Type": "Person", "Entity": "larri young"},{"Boundaries": [[77402, 77414]], "Type": "Person", "Entity": "ramsey lewi"},{"Boundaries": [[38994, 39011]], "Type": "Person", "Entity": "arnold schoenberg"},{"Boundaries": [[50348, 50362], [59927, 59941]], "Type": "Person", "Entity": "charl mingu"},{"Boundaries": [[80891, 80908]], "Type": "Person", "Entity": "harri connick , jr ."},{"Boundaries": [[12040, 12053], [37709, 37722]], "Type": "Person", "Entity": "gerhard kubik"},{"Boundaries": [[28883, 28901], [31157, 31175]], "Type": "Person", "Entity": "fletcher henderson"},{"Boundaries": [[75343, 75357]], "Type": "Person", "Entity": "stanley crouch"},{"Boundaries": [[72267, 72281]], "Type": "Person", "Entity": "eberhard weber"},{"Boundaries": [[61936, 61947], [62409, 62420]], "Type": "Person", "Entity": "hubert law"},{"Boundaries": [[81640, 81652]], "Type": "Person", "Entity": "chri potter"},{"Boundaries": [[69917, 69931]], "Type": "Person", "Entity": "jaco pastoriu"},{"Boundaries": [[77265, 77284]], "Type": "Person", "Entity": "lonni liston smith"},{"Boundaries": [[59961, 59975], [67439, 67453], [67477, 67491], [69715, 69729], [73675, 73689], [78108, 78122]], "Type": "Person", "Entity": "herbi hancock"},{"Boundaries": [[45703, 45715]], "Type": "Person", "Entity": "conrad jani"},{"Boundaries": [[55522, 55534]], "Type": "Person", "Entity": "billi taylor"},{"Boundaries": [[2648, 2663], [25271, 25286], [26234, 26249], [28856, 28871], [73457, 73472]], "Type": "Person", "Entity": "loui armstrong"},{"Boundaries": [[31112, 31124]], "Type": "Person", "Entity": "tommi dorsey"},{"Boundaries": [[81962, 81973]], "Type": "Person", "Entity": "pat metheni"},{"Boundaries": [[10933, 10946]], "Type": "Person", "Entity": "robert palmer"},{"Boundaries": [[33689, 33699]], "Type": "Person", "Entity": "eddi lang"},{"Boundaries": [[16410, 16422], [18070, 18082]], "Type": "Person", "Entity": "scott joplin"},{"Boundaries": [[52722, 52733], [72251, 72262]], "Type": "Person", "Entity": "john surman"},{"Boundaries": [[50644, 50656]], "Type": "Person", "Entity": "albert ayler"},{"Boundaries": [[59943, 59956], [61754, 61767], [62425, 62438], [69890, 69903]], "Type": "Person", "Entity": "wayn shorter"},{"Boundaries": [[9598, 9610], [45444, 45456]], "Type": "Person", "Entity": "eddi condon"},{"Boundaries": [[35326, 35341], [42430, 42445], [42500, 42515], [55502, 55517]], "Type": "Person", "Entity": "dizzi gillespi"},{"Boundaries": [[31177, 31187], [31336, 31346]], "Type": "Person", "Entity": "earl hine"},{"Boundaries": [[50814, 50826]], "Type": "Person", "Entity": "gari peacock"},{"Boundaries": [[61904, 61923]], "Type": "Person", "Entity": "cannonbal adderley"},{"Boundaries": [[55123, 55137]], "Type": "Person", "Entity": "vinc guaraldi"},{"Boundaries": [[59220, 59232]], "Type": "Person", "Entity": "charli byrd"},{"Boundaries": [[81975, 81991]], "Type": "Person", "Entity": "john abercrombi"},{"Boundaries": [[59389, 59404]], "Type": "Person", "Entity": "ella fitzgerald"},{"Boundaries": [[61300, 61311]], "Type": "Person", "Entity": "jimmi smith"},{"Boundaries": [[40427, 40434], [40645, 40652]], "Type": "Person", "Entity": "machito"},{"Boundaries": [[79480, 79489], [80717, 80726]], "Type": "Person", "Entity": "greg osbi"},{"Boundaries": [[16691, 16706], [73242, 73257]], "Type": "Person", "Entity": "wynton marsali"},{"Boundaries": [[47625, 47635], [61818, 61828]], "Type": "Person", "Entity": "art blakey"},{"Boundaries": [[80768, 80780]], "Type": "Person", "Entity": "jame carter"},{"Boundaries": [[81608, 81625]], "Type": "Person", "Entity": "terenc blanchard"},{"Boundaries": [[17842, 17858]], "Type": "Person", "Entity": "william h . krell"},{"Boundaries": [[79465, 79478]], "Type": "Person", "Entity": "steve coleman"},{"Boundaries": [[52495, 52505]], "Type": "Person", "Entity": "steve laci"},{"Boundaries": [[53473, 53486], [72146, 72159]], "Type": "Person", "Entity": "keith jarrett"},{"Boundaries": [[9240, 9255], [28795, 28810]], "Type": "Person", "Entity": "bix beiderbeck"},{"Boundaries": [[63442, 63452]], "Type": "Person", "Entity": "ron carter"},{"Boundaries": [[41727, 41736], [46524, 46533]], "Type": "Person", "Entity": "gil evan"},{"Boundaries": [[46486, 46496]], "Type": "Person", "Entity": "chet baker"},{"Boundaries": [[61783, 61797], [71690, 71704]], "Type": "Person", "Entity": "alic coltran"},{"Boundaries": [[31875, 31887]], "Type": "Person", "Entity": "teddi wilson"},{"Boundaries": [[34715, 34732]], "Type": "Person", "Entity": "tricki sam nanton"},{"Boundaries": [[49614, 49627]], "Type": "Person", "Entity": "howard mcghee"},{"Boundaries": [[31102, 31107]], "Type": "Person", "Entity": "jimmi"},{"Boundaries": [[44438, 44451], [49211, 49224], [50675, 50688], [51604, 51617], [59887, 59900], [82139, 82152]], "Type": "Person", "Entity": "john coltran"},{"Boundaries": [[81993, 82006]], "Type": "Person", "Entity": "john scofield"},{"Boundaries": [[9658, 9668]], "Type": "Person", "Entity": "gene krupa"},{"Boundaries": [[46863, 46874]], "Type": "Person", "Entity": "lar gullin"},{"Boundaries": [[76838, 76854]], "Type": "Person", "Entity": "bugg wesseltoft"},{"Boundaries": [[61282, 61295]], "Type": "Person", "Entity": "jimmi mcgriff"},{"Boundaries": [[31189, 31201]], "Type": "Person", "Entity": "glenn miller"},{"Boundaries": [[45430, 45442]], "Type": "Person", "Entity": "max kaminski"},{"Boundaries": [[17950, 17960]], "Type": "Person", "Entity": "tom turpin"},{"Boundaries": [[37189, 37203], [49641, 49655], [77383, 77397], [82123, 82137]], "Type": "Person", "Entity": "charli parker"},{"Boundaries": [[81657, 81670]], "Type": "Person", "Entity": "joshua redman"},{"Boundaries": [[27358, 27369]], "Type": "Person", "Entity": "eubi blake"},{"Boundaries": [[45686, 45696]], "Type": "Person", "Entity": "lu watter"},{"Boundaries": [[53128, 53144]], "Type": "Person", "Entity": "misha mengelberg"},{"Boundaries": [[16990, 17007], [23984, 24001], [26358, 26375], [30065, 30082]], "Type": "Person", "Entity": "jelli roll morton"},{"Boundaries": [[74928, 74938]], "Type": "Person", "Entity": "chaka khan"},{"Boundaries": [[75045, 75058]], "Type": "Person", "Entity": "david sanborn"},{"Boundaries": [[72195, 72207]], "Type": "Person", "Entity": "jan garbarek"},{"Boundaries": [[74023, 74038]], "Type": "Person", "Entity": "anthoni braxton"},{"Boundaries": [[81591, 81603]], "Type": "Person", "Entity": "roy hargrov"},{"Boundaries": [[50574, 50586], [50881, 50893], [74094, 74106]], "Type": "Person", "Entity": "cecil taylor"},{"Boundaries": [[67785, 67799], [67907, 67921], [68013, 68027]], "Type": "Organisation", "Entity": "weather report"},{"Boundaries": [[78603, 78635]], "Type": "Organisation", "Entity": "jame chanc and the contort"},{"Boundaries": [[67867, 67884]], "Type": "Organisation", "Entity": "return to forev"},{"Boundaries": [[77210, 77221]], "Type": "Organisation", "Entity": "stetsason"},{"Boundaries": [[57813, 57820]], "Type": "Organisation", "Entity": "iraker"},{"Boundaries": [[67889, 67904]], "Type": "Organisation", "Entity": "the headhunt"},{"Boundaries": [[8619, 8643]], "Type": "Organisation", "Entity": "american dialect societi"},{"Boundaries": [[60245, 60262]], "Type": "Organisation", "Entity": "blue note record"},{"Boundaries": [[46553, 46572]], "Type": "Organisation", "Entity": "modern jazz quartet"},{"Boundaries": [[66805, 66829]], "Type": "Organisation", "Entity": "sli and the famili stone"},{"Boundaries": [[72076, 72079]], "Type": "Organisation", "Entity": "ecm"},{"Boundaries": [[26618, 26646]], "Type": "Organisation", "Entity": "origin dixieland jass band"},{"Boundaries": [[76780, 76785]], "Type": "Organisation", "Entity": "kobol"},{"Boundaries": [[76755, 76778]], "Type": "Organisation", "Entity": "the cinemat orchestra"},{"Boundaries": [[76856, 76868]], "Type": "Organisation", "Entity": "jaga jazzist"},{"Boundaries": [[77097, 77107]], "Type": "Organisation", "Entity": "gang starr"},{"Boundaries": [[67115, 67141]], "Type": "Organisation", "Entity": "the toni william lifetim"},{"Boundaries": [[72176, 72193]], "Type": "Organisation", "Entity": "pat metheni group"},{"Boundaries": [[76648, 76657]], "Type": "Organisation", "Entity": "jazzanova"},{"Boundaries": [[72481, 72487], [72923, 72929]], "Type": "Organisation", "Entity": "senat"},{"Boundaries": [[76662, 76676]], "Type": "Organisation", "Entity": "fila brazillia"},{"Boundaries": [[33846, 33858]], "Type": "Organisation", "Entity": "okeh record"},{"Boundaries": [[67804, 67824], [71984, 72004]], "Type": "Organisation", "Entity": "mahavishnu orchestra"},{"Boundaries": [[80352, 80364], [80544, 80556]], "Type": "Organisation", "Entity": "the bad plu"},{"Boundaries": [[70966, 70977]], "Type": "Organisation", "Entity": "headhunt"},{"Boundaries": [[72452, 72476], [72865, 72889]], "Type": "Organisation", "Entity": "hous of repres"},{"Boundaries": [[70005, 70013]], "Type": "Organisation", "Entity": "casiopea"},{"Boundaries": [[76795, 76804]], "Type": "PopulatedPlace", "Entity": "norwegian"},{"Boundaries": [[11436, 11448]], "Type": "PopulatedPlace", "Entity": "southeastern"},{"Boundaries": [[44, 51], [233, 240], [635, 642], [3404, 3411], [5264, 5280], [8208, 8225], [8273, 8280], [9867, 9874], [9923, 9930], [10150, 10157], [10270, 10278], [10485, 10492], [10510, 10517], [10572, 10579], [10710, 10723], [12813, 12829], [12841, 12848], [13418, 13425], [13465, 13472], [13598, 13605], [13663, 13676], [13857, 13864], [13972, 13988], [14188, 14204], [14801, 14808], [15049, 15065], [15331, 15338], [15377, 15393], [15905, 15921], [16600, 16616], [17213, 17220], [17613, 17629], [18019, 18035], [18511, 18524], [19117, 19124], [19217, 19233], [19432, 19439], [20573, 20589], [22816, 22832], [23073, 23089], [23346, 23362], [25187, 25200], [25786, 25802], [33079, 33095], [37806, 37821], [37957, 37964], [38281, 38288], [39883, 39899], [39961, 39968], [40857, 40864], [41006, 41013], [42184, 42191], [42274, 42290], [42334, 42341], [43373, 43386], [43518, 43525], [43864, 43871], [44035, 44042], [53984, 53991], [61434, 61450], [61521, 61537], [61642, 61649], [61716, 61731], [62007, 62014], [62158, 62165], [62342, 62349], [62452, 62459], [62628, 62635], [63165, 63172], [63389, 63396], [63798, 63816], [67681, 67693], [70425, 70432], [74549, 74565], [79412, 79428]], "Type": "PopulatedPlace", "Entity": "african"},{"Boundaries": [[1048, 1059], [2963, 2974], [6327, 6338], [9048, 9059], [10802, 10813], [11578, 11589], [12608, 12619], [12751, 12762], [12932, 12943], [13243, 13254], [14579, 14590], [15559, 15570], [16114, 16125], [16655, 16666], [16737, 16748], [16971, 16982], [22361, 22372], [22387, 22398], [22675, 22686], [23160, 23171], [23593, 23604], [24290, 24301], [25984, 25995], [26293, 26304], [28442, 28453], [28549, 28560], [28958, 28969], [30101, 30112], [30797, 30814], [45010, 45021], [45569, 45580], [56866, 56877]], "Type": "PopulatedPlace", "Entity": "new orlean"},{"Boundaries": [[2893, 2900], [8976, 8983], [9454, 9461], [9473, 9480], [9624, 9631], [24117, 24124], [28647, 28654], [30647, 30654], [31417, 31424], [46974, 46981]], "Type": "PopulatedPlace", "Entity": "chicago"},{"Boundaries": [[15548, 15554]], "Type": "PopulatedPlace", "Entity": "havana"},{"Boundaries": [[40676, 40689], [46245, 46258], [57085, 57098], [57703, 57716], [78308, 78321]], "Type": "PopulatedPlace", "Entity": "new york citi"},{"Boundaries": [[24129, 24137], [27265, 27273], [28023, 28031], [30613, 30621], [37264, 37272], [42247, 42255], [79442, 79450]], "Type": "PopulatedPlace", "Entity": "new york"},{"Boundaries": [[28482, 28493]], "Type": "PopulatedPlace", "Entity": "lo angel"},{"Boundaries": [[28464, 28477]], "Type": "PopulatedPlace", "Entity": "san francisco"},{"Boundaries": [[53818, 53831], [59106, 59119]], "Type": "PopulatedPlace", "Entity": "latin america"},{"Boundaries": [[13648, 13661], [59140, 59153]], "Type": "PopulatedPlace", "Entity": "north america"},{"Boundaries": [[150, 163], [3605, 3618], [9375, 9388], [10286, 10299], [10918, 10931], [13716, 13729], [15825, 15838], [19283, 19296], [27140, 27153], [42056, 42069]], "Type": "PopulatedPlace", "Entity": "unit state"},{"Boundaries": [[27335, 27344]], "Type": "PopulatedPlace", "Entity": "baltimor"},{}]