[{"Boundaries": [[98, 106], [216, 224], [1597, 1605], [1692, 1700]], "Type": "PopulatedPlace", "Entity": "cameroon"},{"Boundaries": [[685, 691]], "Type": "PopulatedPlace", "Entity": "malabo"},{"Boundaries": [[229, 234], [1610, 1615], [1727, 1732]], "Type": "PopulatedPlace", "Entity": "gabon"},{"Boundaries": [[2437, 2447]], "Type": "PopulatedPlace", "Entity": "mikomeseng"},{"Boundaries": [[61, 67], [1550, 1556]], "Type": "PopulatedPlace", "Entity": "africa"},{"Boundaries": [[16, 33], [3704, 3721], [4042, 4059]], "Type": "PopulatedPlace", "Entity": "equatori guinea"},{}]