[{"Boundaries": [[1506, 1521], [4912, 4927]], "Type": "Person", "Entity": "masatoshi shima"},{"Boundaries": [[1199, 1214]], "Type": "Person", "Entity": "federico faggin"},{"Boundaries": [[34873, 34876], [35231, 35235]], "Type": "Organisation", "Entity": "snk"},{"Boundaries": [[1248, 1253], [1408, 1413], [4665, 4670], [8725, 8728], [8744, 8749], [9141, 9149], [11943, 11952], [13818, 13819], [18704, 18708], [29835, 29845], [29881, 29883]], "Type": "Organisation", "Entity": "intel"},{"Boundaries": [[32249, 32257], [32299, 32309], [32418, 32423]], "Type": "Organisation", "Entity": "ibm"},{"Boundaries": [[314, 328], [22507, 22515], [31193, 31203]], "Type": "Organisation", "Entity": "mo technolog"},{"Boundaries": [[27223, 27225], [27386, 27389]], "Type": "Organisation", "Entity": "kawasaki"},{"Boundaries": [[30922, 30928]], "Type": "Organisation", "Entity": "sinclair research"},{"Boundaries": [[30587, 30591]], "Type": "Organisation", "Entity": "xerox"},{"Boundaries": [[23873, 23878]], "Type": "Organisation", "Entity": "stmicroelectron"},{"Boundaries": [[34524, 34526], [34590, 34593], [34664, 34667]], "Type": "Organisation", "Entity": "namco"},{"Boundaries": [[30402, 30405]], "Type": "Organisation", "Entity": "kaypro"},{"Boundaries": [[36345, 36346], [37017, 37029]], "Type": "Organisation", "Entity": "roland"},{"Boundaries": [[33722, 33730]], "Type": "Organisation", "Entity": "adaptec"},{"Boundaries": [[34821, 34827], [35033, 35038], [35057, 35059], [35146, 35149]], "Type": "Organisation", "Entity": "sega"},{"Boundaries": [[36032, 36045]], "Type": "Organisation", "Entity": "texa instrument"},{"Boundaries": [[4, 9], [53, 58], [426, 431], [754, 759], [835, 840], [1282, 1287], [13726, 13728], [13897, 13907], [16862, 16865], [21976, 21986], [22792, 22795], [22831, 22836], [23799, 23810], [24504, 24508], [25733, 25735], [26420, 26424], [26458, 26460], [29854, 29855], [31901, 31915]], "Type": "Organisation", "Entity": "zilog"},{"Boundaries": [[23923, 23926], [24285, 24288], [24380, 24383], [26351, 26354]], "Type": "Organisation", "Entity": "sharp"},{"Boundaries": [[31461, 31464]], "Type": "Organisation", "Entity": "microsoft"},{"Boundaries": [[37297, 37300]], "Type": "Organisation", "Entity": "lexicon"},{"Boundaries": [[33652, 33654]], "Type": "Organisation", "Entity": "verifon"},{"Boundaries": [[697, 704], [24401, 24403], [26066, 26072], [26376, 26378], [27984, 27991]], "Type": "Organisation", "Entity": "toshiba"},{"Boundaries": [[34855, 34858]], "Type": "Organisation", "Entity": "capcom"},{"Boundaries": [[35465, 35471]], "Type": "Organisation", "Entity": "sharp corpor"},{"Boundaries": [[28623, 28637]], "Type": "Organisation", "Entity": "ascii corpor"},{"Boundaries": [[23686, 23697], [29688, 29693], [31012, 31017], [31034, 31042]], "Type": "Organisation", "Entity": "amstrad"},{"Boundaries": [[25194, 25205]], "Type": "PopulatedPlace", "Entity": "soviet union"},{"Boundaries": [[25005, 25010]], "Type": "PopulatedPlace", "Entity": "romania"},{"Boundaries": [[24717, 24727]], "Type": "PopulatedPlace", "Entity": "east germani"},{}]